{"project_name": "house", "url": "https://drive.google.com/drive/u/0/folders/1FVes1ZmfgVHLLBH-MXGR-KusoNDcpzga", "choice": "1", "preferred": "1", "files counter": 1, "lines counter": 21613, "categories": ["id", "date", "price", "bedrooms", "bathrooms", "sqft_living", "sqft_lot", "floors", "waterfront", "view", "condition", "grade", "sqft_above", "sqft_basement", "yr_built", "yr_renovated", "zipcode", "lat", "long", "sqft_living15", "sqft_lot15"], "missing": "drop", "target": 2, "prediction": "price", "cols": [""], "lines counter after cleaning": 21608, "epochs": 50, "alpha": 0.1}